abscab/__init__.py
abscab/_abscab.py
abscab/_bulirsch_cel.py
abscab/_compsum.py
abscab-1.0.0.dist-info/LICENSE
abscab-1.0.0.dist-info/METADATA
abscab-1.0.0.dist-info/WHEEL
abscab-1.0.0.dist-info/top_level.txt
abscab-1.0.0.dist-info/RECORD
