Metadata-Version: 2.1
Name: abscab
Version: 1.0.0
Summary: Accurate Biot-Savart routines with Correct Asymptotic Behaviour
Author-email: Jonathan Schilling <jonathan.schilling@mail.de>
License: Apache 2.0
Classifier: Programming Language :: Python :: 3
Requires-Python: >=3.7
License-File: LICENSE
Requires-Dist: numpy
